easy_bert/__init__.py
easy_bert/adversarial.py
easy_bert/tinybert_distiller.py
easy_bert/vocab.py
easy_bert/base/__init__.py
easy_bert/base/base_predictor.py
easy_bert/base/base_trainer.py
easy_bert/bert4classification/__init__.py
easy_bert/bert4classification/classification_model.py
easy_bert/bert4classification/classification_predictor.py
easy_bert/bert4classification/classification_trainer.py
easy_bert/bert4pretraining/__init__.py
easy_bert/bert4pretraining/mlm_trainer.py
easy_bert/bert4sequence_labeling/__init__.py
easy_bert/bert4sequence_labeling/sequence_labeling_model.py
easy_bert/bert4sequence_labeling/sequence_labeling_predictor.py
easy_bert/bert4sequence_labeling/sequence_labeling_trainer.py
easy_bert/losses/__init__.py
easy_bert/losses/crf_layer.py
easy_bert/losses/focal_loss.py
easy_bert/losses/label_smoothing_loss.py
tests/__init__.py
tests/test_bert4classification.py
tests/test_bert4sequence_labeling.py
tests/test_crf_layer.py
tests/test_fp16.py
tests/test_label_smoothing_ce.py
tests/test_mlm.py
tests/test_onnx.py
tests/test_tinybert_distiller.py
tests/test_warmup.py
easy_zh_bert-0.6.0.dist-info/LICENSE
easy_zh_bert-0.6.0.dist-info/METADATA
easy_zh_bert-0.6.0.dist-info/WHEEL
easy_zh_bert-0.6.0.dist-info/top_level.txt
easy_zh_bert-0.6.0.dist-info/RECORD
