Metadata-Version: 2.1
Name: easy-zh-bert
Version: 0.6.0
Summary: easy-bert是一个中文NLP工具，提供诸多bert变体调用和调参方法，极速上手；清晰的设计和代码注释，也很适合学习
Home-page: https://github.com/waking95/easy-bert
Author: waking95
Author-email: wang0624@foxmail.com
License: MIT
Project-URL: Bug Tracker, https://github.com/waking95/easy-bert/issues
Platform: UNKNOWN
Classifier: Programming Language :: Python :: 3
Classifier: License :: OSI Approved :: MIT License
Classifier: Operating System :: OS Independent
Classifier: Topic :: Scientific/Engineering :: Artificial Intelligence
License-File: LICENSE
Requires-Dist: torch (==1.6.0)
Requires-Dist: transformers (==3.1.0)
Requires-Dist: scikit-learn (==0.24.0)
Requires-Dist: numpy (==1.17.0)
Requires-Dist: datasets (==1.16.0)
Requires-Dist: textbrewer (==0.2.0)
Requires-Dist: onnxruntime-gpu (==1.4.0)
